hjb_pyusb/_hjb_pyusb.so
hjb_pyusb/hjb_pyusb.py
hjb_pyusb/libutcl-2.so
hjb_pyusb/libutcl-2.so.0
hjb_pyusb/libutcl-2.so.0.0.0
hjb_pyusb-3.0.0.dist-info/METADATA
hjb_pyusb-3.0.0.dist-info/WHEEL
hjb_pyusb-3.0.0.dist-info/top_level.txt
hjb_pyusb-3.0.0.dist-info/RECORD
